README.md
setup.cfg
setup.py
yalebuildings/__init__.py
yalebuildings/main.py
yalebuildings.egg-info/PKG-INFO
yalebuildings.egg-info/SOURCES.txt
yalebuildings.egg-info/dependency_links.txt
yalebuildings.egg-info/requires.txt
yalebuildings.egg-info/top_level.txt