Metadata-Version: 1.0
Name: yalebuildings
Version: 0.1.0
Summary: Library for fetching data from the Yale Buildings API.
Home-page: https://github.com/ErikBoesen/yalebuildings
Author: Erik Boesen
Author-email: me@erikboesen.com
License: GPL
Platform: UNKNOWN
